<?xml version="1.0" encoding="UTF-8"?>
<Tokens version="1.0">
	<File path="Constants/DJIHotpointMissionExecutionState.html">
		
		<Token>
			<TokenIdentifier>//apple_ref/c/tdef/DJIHotpointMissionExecutionState</TokenIdentifier>
			<Abstract type="html">All possible hot point mission execution states.</Abstract>
			<DeclaredIn>DJIHotPointMission.h</DeclaredIn>
            
			
			<NodeRef refid="125"/>
		</Token>
		
		
        
        <Token>
            <TokenIdentifier>//apple_ref/c/econst/DJIHotpointMissionExecutionStateInitializing</TokenIdentifier>
            <Abstract type="html">The mission has been started and the aircraft is flying to the start point.
     </Abstract>
            <Declaration>DJIHotpointMissionExecutionStateInitializing</Declaration>
            
            <DeclaredIn>DJIHotPointMission.h</DeclaredIn>
            
            <NodeRef refid="125"/>
        </Token>
        
        <Token>
            <TokenIdentifier>//apple_ref/c/econst/DJIHotpointMissionExecutionStateMoving</TokenIdentifier>
            <Abstract type="html">The aircraft is currently moving.
     </Abstract>
            <Declaration>DJIHotpointMissionExecutionStateMoving</Declaration>
            
            <DeclaredIn>DJIHotPointMission.h</DeclaredIn>
            
            <NodeRef refid="125"/>
        </Token>
        
        <Token>
            <TokenIdentifier>//apple_ref/c/econst/DJIHotpointMissionExecutionStatePaused</TokenIdentifier>
            <Abstract type="html">The mission is currently paused by the user.
     </Abstract>
            <Declaration>DJIHotpointMissionExecutionStatePaused</Declaration>
            
            <DeclaredIn>DJIHotPointMission.h</DeclaredIn>
            
            <NodeRef refid="125"/>
        </Token>
        
	</File>
</Tokens>