<?xml version="1.0" encoding="UTF-8"?>
<Tokens version="1.0">
	<File path="Protocols/DJINavigationDelegate.html">
		
		<Token>
			<TokenIdentifier>//apple_ref/occ/intf/DJINavigationDelegate</TokenIdentifier>
			<Abstract type="html"></Abstract>
			<DeclaredIn>DJINavigation.h</DeclaredIn>
            
			
			<NodeRef refid="69"/>
		</Token>
		
		
		<Token>
			<TokenIdentifier>//apple_ref/occ/intfm/DJINavigationDelegate/onNavigationMissionStatusChanged:</TokenIdentifier>
			<Abstract type="html">Updates the navigation mission status. If the missionType is of type DJINavigationMissionWaypoint
then the missionStatus will be of class DJIWaypointMissionStatus. If missionType is
DJINavigationMissionHotpoint then the missionStatus will be of class DJIHotpointMissionStatus.
If the missionType is DJINavigationMissionFollowMe then the missionStatus will be of class DJIFollowMeMissionStatus.</Abstract>
			<DeclaredIn>DJINavigation.h</DeclaredIn>
			
			<Declaration>- (void)onNavigationMissionStatusChanged:(DJINavigationMissionStatus *)missionStatus</Declaration>
			<Parameters>
				<Parameter>
					<Name>missionStatus</Name>
					<Abstract type="html">Mission status based on the current mission.</Abstract>
				</Parameter>
			</Parameters>
			
			<Anchor>//api/name/onNavigationMissionStatusChanged:</Anchor>
            <NodeRef refid="69"/>
		</Token>
		
        
        
	</File>
</Tokens>