<?xml version="1.0" encoding="UTF-8"?>
<Tokens version="1.0">
	<File path="Constants/DJICameraDigitalFilter.html">
		
		<Token>
			<TokenIdentifier>//apple_ref/c/tdef/DJICameraDigitalFilter</TokenIdentifier>
			<Abstract type="html">Camera digital filters. The default value is DJICameraDigitalFilterNone.</Abstract>
			<DeclaredIn>DJICameraSettingsDef.h</DeclaredIn>
            
			
			<NodeRef refid="82"/>
		</Token>
		
		
        
        <Token>
            <TokenIdentifier>//apple_ref/c/econst/DJICameraDigitalFilterNone</TokenIdentifier>
            <Abstract type="html">The digital filter is set to none or no filter.
     </Abstract>
            <Declaration>DJICameraDigitalFilterNone</Declaration>
            
            <DeclaredIn>DJICameraSettingsDef.h</DeclaredIn>
            
            <NodeRef refid="82"/>
        </Token>
        
        <Token>
            <TokenIdentifier>//apple_ref/c/econst/DJICameraDigitalFilterArt</TokenIdentifier>
            <Abstract type="html">The digital filter is set to art.
     </Abstract>
            <Declaration>DJICameraDigitalFilterArt</Declaration>
            
            <DeclaredIn>DJICameraSettingsDef.h</DeclaredIn>
            
            <NodeRef refid="82"/>
        </Token>
        
        <Token>
            <TokenIdentifier>//apple_ref/c/econst/DJICameraDigitalFilterReminiscence</TokenIdentifier>
            <Abstract type="html">The digital filter is set to reminiscence.
     </Abstract>
            <Declaration>DJICameraDigitalFilterReminiscence</Declaration>
            
            <DeclaredIn>DJICameraSettingsDef.h</DeclaredIn>
            
            <NodeRef refid="82"/>
        </Token>
        
        <Token>
            <TokenIdentifier>//apple_ref/c/econst/DJICameraDigitalFilterInverse</TokenIdentifier>
            <Abstract type="html">The digital filter is set to inverse.
     </Abstract>
            <Declaration>DJICameraDigitalFilterInverse</Declaration>
            
            <DeclaredIn>DJICameraSettingsDef.h</DeclaredIn>
            
            <NodeRef refid="82"/>
        </Token>
        
        <Token>
            <TokenIdentifier>//apple_ref/c/econst/DJICameraDigitalFilterBlackAndWhite</TokenIdentifier>
            <Abstract type="html">The digital filter is set to black and white.
     </Abstract>
            <Declaration>DJICameraDigitalFilterBlackAndWhite</Declaration>
            
            <DeclaredIn>DJICameraSettingsDef.h</DeclaredIn>
            
            <NodeRef refid="82"/>
        </Token>
        
        <Token>
            <TokenIdentifier>//apple_ref/c/econst/DJICameraDigitalFilterBright</TokenIdentifier>
            <Abstract type="html">The digital filter is set to bright.
     </Abstract>
            <Declaration>DJICameraDigitalFilterBright</Declaration>
            
            <DeclaredIn>DJICameraSettingsDef.h</DeclaredIn>
            
            <NodeRef refid="82"/>
        </Token>
        
        <Token>
            <TokenIdentifier>//apple_ref/c/econst/DJICameraDigitalFilterMovie</TokenIdentifier>
            <Abstract type="html">The digital filter is set to movie.
     </Abstract>
            <Declaration>DJICameraDigitalFilterMovie</Declaration>
            
            <DeclaredIn>DJICameraSettingsDef.h</DeclaredIn>
            
            <NodeRef refid="82"/>
        </Token>
        
        <Token>
            <TokenIdentifier>//apple_ref/c/econst/DJICameraDigitalFilterPunk</TokenIdentifier>
            <Abstract type="html">This digital filter is currently not supported.
     </Abstract>
            <Declaration>DJICameraDigitalFilterPunk</Declaration>
            
            <DeclaredIn>DJICameraSettingsDef.h</DeclaredIn>
            
            <NodeRef refid="82"/>
        </Token>
        
        <Token>
            <TokenIdentifier>//apple_ref/c/econst/DJICameraDigitalFilterPopArt</TokenIdentifier>
            <Abstract type="html">This digital filter is currently not supported.
     </Abstract>
            <Declaration>DJICameraDigitalFilterPopArt</Declaration>
            
            <DeclaredIn>DJICameraSettingsDef.h</DeclaredIn>
            
            <NodeRef refid="82"/>
        </Token>
        
        <Token>
            <TokenIdentifier>//apple_ref/c/econst/DJICameraDigitalFilterWedding</TokenIdentifier>
            <Abstract type="html">This digital filter is currently not supported.
     </Abstract>
            <Declaration>DJICameraDigitalFilterWedding</Declaration>
            
            <DeclaredIn>DJICameraSettingsDef.h</DeclaredIn>
            
            <NodeRef refid="82"/>
        </Token>
        
        <Token>
            <TokenIdentifier>//apple_ref/c/econst/DJICameraDigitalFilterTinyHole</TokenIdentifier>
            <Abstract type="html">This digital filter is currently not supported.
     </Abstract>
            <Declaration>DJICameraDigitalFilterTinyHole</Declaration>
            
            <DeclaredIn>DJICameraSettingsDef.h</DeclaredIn>
            
            <NodeRef refid="82"/>
        </Token>
        
        <Token>
            <TokenIdentifier>//apple_ref/c/econst/DJICameraDigitalFilterMiniature</TokenIdentifier>
            <Abstract type="html">This digital filter is currently not supported.
     </Abstract>
            <Declaration>DJICameraDigitalFilterMiniature</Declaration>
            
            <DeclaredIn>DJICameraSettingsDef.h</DeclaredIn>
            
            <NodeRef refid="82"/>
        </Token>
        
        <Token>
            <TokenIdentifier>//apple_ref/c/econst/DJICameraDigitalFilterOilPainting</TokenIdentifier>
            <Abstract type="html">This digital filter is currently not supported.
     </Abstract>
            <Declaration>DJICameraDigitalFilterOilPainting</Declaration>
            
            <DeclaredIn>DJICameraSettingsDef.h</DeclaredIn>
            
            <NodeRef refid="82"/>
        </Token>
        
        <Token>
            <TokenIdentifier>//apple_ref/c/econst/DJICameraDigitalFilterWaterColor</TokenIdentifier>
            <Abstract type="html">This digital filter is currently not supported.
     </Abstract>
            <Declaration>DJICameraDigitalFilterWaterColor</Declaration>
            
            <DeclaredIn>DJICameraSettingsDef.h</DeclaredIn>
            
            <NodeRef refid="82"/>
        </Token>
        
        <Token>
            <TokenIdentifier>//apple_ref/c/econst/DJICameraDigitalFilterM31</TokenIdentifier>
            <Abstract type="html">The digital filter is set to M31.
     </Abstract>
            <Declaration>DJICameraDigitalFilterM31</Declaration>
            
            <DeclaredIn>DJICameraSettingsDef.h</DeclaredIn>
            
            <NodeRef refid="82"/>
        </Token>
        
        <Token>
            <TokenIdentifier>//apple_ref/c/econst/DJICameraDigitalFilterDelta</TokenIdentifier>
            <Abstract type="html">The digital filter is set to delta.
     </Abstract>
            <Declaration>DJICameraDigitalFilterDelta</Declaration>
            
            <DeclaredIn>DJICameraSettingsDef.h</DeclaredIn>
            
            <NodeRef refid="82"/>
        </Token>
        
        <Token>
            <TokenIdentifier>//apple_ref/c/econst/DJICameraDigitalFilterkDX</TokenIdentifier>
            <Abstract type="html">The digital filter is set to kDX.
     </Abstract>
            <Declaration>DJICameraDigitalFilterkDX</Declaration>
            
            <DeclaredIn>DJICameraSettingsDef.h</DeclaredIn>
            
            <NodeRef refid="82"/>
        </Token>
        
        <Token>
            <TokenIdentifier>//apple_ref/c/econst/DJICameraDigitalFilterDK79</TokenIdentifier>
            <Abstract type="html">The digital filter is set to DK79.
     </Abstract>
            <Declaration>DJICameraDigitalFilterDK79</Declaration>
            
            <DeclaredIn>DJICameraSettingsDef.h</DeclaredIn>
            
            <NodeRef refid="82"/>
        </Token>
        
        <Token>
            <TokenIdentifier>//apple_ref/c/econst/DJICameraDigitalFilterPrismo</TokenIdentifier>
            <Abstract type="html">The digital filter is set to prismo.
     </Abstract>
            <Declaration>DJICameraDigitalFilterPrismo</Declaration>
            
            <DeclaredIn>DJICameraSettingsDef.h</DeclaredIn>
            
            <NodeRef refid="82"/>
        </Token>
        
        <Token>
            <TokenIdentifier>//apple_ref/c/econst/DJICameraDigitalFilterJugo</TokenIdentifier>
            <Abstract type="html">The digital filter is set to jugo.
     </Abstract>
            <Declaration>DJICameraDigitalFilterJugo</Declaration>
            
            <DeclaredIn>DJICameraSettingsDef.h</DeclaredIn>
            
            <NodeRef refid="82"/>
        </Token>
        
        <Token>
            <TokenIdentifier>//apple_ref/c/econst/DJICameraDigitalFilterVision4</TokenIdentifier>
            <Abstract type="html">The digital filter is set to vision 4.
     </Abstract>
            <Declaration>DJICameraDigitalFilterVision4</Declaration>
            
            <DeclaredIn>DJICameraSettingsDef.h</DeclaredIn>
            
            <NodeRef refid="82"/>
        </Token>
        
        <Token>
            <TokenIdentifier>//apple_ref/c/econst/DJICameraDigitalFilterVision6</TokenIdentifier>
            <Abstract type="html">The digital filter is set to vision 6.
     </Abstract>
            <Declaration>DJICameraDigitalFilterVision6</Declaration>
            
            <DeclaredIn>DJICameraSettingsDef.h</DeclaredIn>
            
            <NodeRef refid="82"/>
        </Token>
        
        <Token>
            <TokenIdentifier>//apple_ref/c/econst/DJICameraDigitalFilterVisionX</TokenIdentifier>
            <Abstract type="html">The digital filter is set to vision x.
     </Abstract>
            <Declaration>DJICameraDigitalFilterVisionX</Declaration>
            
            <DeclaredIn>DJICameraSettingsDef.h</DeclaredIn>
            
            <NodeRef refid="82"/>
        </Token>
        
        <Token>
            <TokenIdentifier>//apple_ref/c/econst/DJICameraDigitalFilterNeutral</TokenIdentifier>
            <Abstract type="html">The digital filter is set to neutral.
     </Abstract>
            <Declaration>DJICameraDigitalFilterNeutral</Declaration>
            
            <DeclaredIn>DJICameraSettingsDef.h</DeclaredIn>
            
            <NodeRef refid="82"/>
        </Token>
        
        <Token>
            <TokenIdentifier>//apple_ref/c/econst/DJICameraDigitalFilterUnknown</TokenIdentifier>
            <Abstract type="html">The digital filter is unknown.
     </Abstract>
            <Declaration>DJICameraDigitalFilterUnknown</Declaration>
            
            <DeclaredIn>DJICameraSettingsDef.h</DeclaredIn>
            
            <NodeRef refid="82"/>
        </Token>
        
	</File>
</Tokens>